maquina.v
module maquina(
    input clk, reset, insere,
    input [4:1] numero,
    output reg LED = 0,
    output reg A, B, C, D, E, F, G
);
    parameter inicial = 4'b1110;
    parameter cinco = 4'b0101;
    parameter nove = 4'b1001;
    parameter zero = 4'b0000;
    parameter nove_final= 4'b0010;
    parameter oito = 4'b1000;
    parameter um = 4'b0001;
    parameter falha = 4'b1111;

    reg [3:0] estado;
    reg [3:0] proximo_estado;
    
    reg teste1 = 0;
    reg teste2 = 0;
    reg teste3 = 0;

    always @(posedge clk) begin
        if (reset)  begin
            estado <= inicial;
            LED = 0;
        end
        else begin 
            estado <= proximo_estado;
        end
    end

    always @(posedge clk) begin
        proximo_estado = estado;
        case (estado)
            um:
                proximo_estado = um;
            falha:
                proximo_estado = falha;
            inicial:
                if (numero == 4'b0101) proximo_estado = cinco;
                else begin
                    if (LED) proximo_estado = falha;
                    else begin
                        proximo_estado = inicial;
                        LED = 1'b1;
                    end
                end
            cinco:
                if (LED) begin
                    if (numero == 4'b1001) proximo_estado = nove;
                    else                proximo_estado = falha;
                end
                else begin
                    if (numero == 4'b1001) proximo_estado = nove;
                    else begin
                        proximo_estado = cinco;
                        LED = 1;
                    end
                end
            nove:
                if (LED) begin
                    if (numero == 4'b0000) proximo_estado =zero;
                    else                proximo_estado = falha;
                end
                else begin
                    if (numero == 4'b0000) proximo_estado =zero;
                    else begin
                        proximo_estado = nove;
                        LED = 1;
                    end
                end
            zero: begin
                teste3 = 0;
                if (LED) begin
                    teste1 = 0;
                    if (numero == 4'b0010) proximo_estado = nove_final;
                    else                proximo_estado = falha;
                end
                else begin
                    teste2 =1;
                    if (numero == 4'b0010) proximo_estado = nove_final;
                    else begin
                        proximo_estado = zero;
                        LED = 1;
                    end
                end
            end
            nove_final:
                if (LED) begin
                    if (numero == 4'b1000) proximo_estado = oito;
                    else                proximo_estado = falha;
                end
                else begin
                    if (numero == 4'b1000) proximo_estado = oito;
                    else begin
                        proximo_estado = nove_final;
                        LED = 1;
                    end
                end
            oito:
                if(LED) begin
                    if (numero == 4'b0001) proximo_estado = um;
                    else                proximo_estado = falha;
                end
                else begin
                    if (numero == 4'b0001) proximo_estado = um;
                    else begin
                        proximo_estado = oito;
                        LED = 1;
                    end
                end
            default:
                proximo_estado = inicial;
        endcase
    end
    always @(estado) begin
        if (estado == um & LED == 1) begin
            A <= 1'b0;
            B <= 1'b0;
            C <= 1'b1;
            D <= 1'b1;
            E <= 1'b0;
            F <= 1'b0;
            G <= 1'b0;
        end

        else if (estado == um & LED == 0) begin
            A <= 1'b0;
            B <= 1'b1;
            C <= 1'b0;
            D <= 1'b0;
            E <= 1'b1;
            F <= 1'b0;
            G <= 1'b0;
        end
        else if (estado == falha) begin
            A <= 1'b0;
            B <= 1'b1;
            C <= 1'b1;
            D <= 1'b1;
            E <= 1'b0;
            F <= 1'b0;
            G <= 1'b0;
        end
        else begin
            A <= ~(((~numero[4])&numero[2])|((~numero[4])&(~numero[3])&(~numero[1]))|((~numero[4])&numero[3]&numero[1])|(numero[4]&(~numero[3])&(~numero[2])));
            B <= ~(((~numero[4])&(~numero[3]))|((~numero[3]&(~numero[2])))|((~numero[4])&(~numero[2])&(~numero[1]))|((~numero[4])&numero[2]&numero[1]));
            C <= ~(((~numero[3])&(~numero[2]))|((~numero[4])&numero[1])|((~numero[4])&numero[3]));
            D <= ~(((~numero[4])&(~numero[3])&(~numero[1]))|((~numero[4])&(~numero[3])&numero[2])|((~numero[4])&numero[2]&(~numero[1]))|(numero[4]&(~numero[3])&(~numero[2]))|((~numero[4])&(numero[3])&(~numero[2])&numero[1]));
            E <= ~(((~numero[3])&(~numero[2])&(~numero[1]))|((~numero[4])&numero[2]&(~numero[1])));
            F <= ~(((~numero[4])&(~numero[2])&(~numero[1]))|((~numero[4])&numero[3]&(~numero[2]))|((~numero[4])&numero[3]&(~numero[1]))|(numero[4]&(~numero[3])&(~numero[2])));
            G <= ~((numero[4]|((~numero[3])&numero[2])|(numero[2]&(~numero[1]))|(numero[3]&(~numero[2]))));
        end
    end
endmodule

maquina_tb.v
`include "./maquina.v"
module maquina_tb ();
    reg clk, reset, insere;
    reg [4:1] numero;
    wire LED, A, B, C, D, E, F, G;


    maquina tb_maquina(.clk(clk), .reset(reset), .insere(insere), .numero(numero), .LED(LED), .A(A), .B(B), .C(C), .D(D), .E(E), .F(F), .G(G));

    always begin
        #5
        clk <= ~clk;
        insere <= ~insere;
    end
    initial begin
        $dumpfile("maquina.vcd");
        $dumpvars;
        $display("numero A B C D E F G LED");
        $monitor("%b%b%b%b   %b %b %b %b %b %b %b %b %b",numero[4],numero[3], numero[2], numero[1], A,B,C,D,E,F,G,LED,reset);

        reset = 1'b1;
        clk = 1; insere = 1;
        numero = 4'b0101;
        reset = 0;

        #30
        numero = 4'b1001;

        #20
        numero = 4'b0000;

        #20
        numero = 4'b0010;

        #20
        numero = 4'b1000;

        #20
        numero = 4'b0001;

//-------------------------------------------------------------------------------------

        #20
        reset = 1'b1;
        #20
        reset = 0;
        numero = 4'b0101;


        #20
        numero = 4'b1001;

        #20
        numero = 4'b0100;

        #10
        numero = 4'b0000;

        #20
        numero = 4'b0010;

        #20
        numero = 4'b1000;

        #20
        numero = 4'b0001;
        #10 $finish;
    end
endmodule

maquina.vcd
$date
	Wed Jan 15 10:48:36 2025
$end
$version
	Icarus Verilog
$end
$timescale
	1s
$end
$scope module maquina_tb $end
$var wire 1 ! LED $end
$var wire 1 " G $end
$var wire 1 # F $end
$var wire 1 $ E $end
$var wire 1 % D $end
$var wire 1 & C $end
$var wire 1 ' B $end
$var wire 1 ( A $end
$var reg 1 ) clk $end
$var reg 1 * insere $end
$var reg 4 + numero [4:1] $end
$var reg 1 , reset $end
$scope module tb_maquina $end
$var wire 1 ) clk $end
$var wire 1 * insere $end
$var wire 4 - numero [4:1] $end
$var wire 1 , reset $end
$var reg 1 ( A $end
$var reg 1 ' B $end
$var reg 1 & C $end
$var reg 1 % D $end
$var reg 1 $ E $end
$var reg 1 # F $end
$var reg 1 " G $end
$var reg 1 ! LED $end
$var reg 4 . estado [3:0] $end
$var reg 4 / proximo_estado [3:0] $end
$var reg 1 0 teste1 $end
$var reg 1 1 teste2 $end
$var reg 1 2 teste3 $end
$upscope $end
$upscope $end
$enddefinitions $end
#0
$dumpvars
02
01
00
b1110 /
b1110 .
b101 -
0,
b101 +
1*
1)
0(
1'
0&
0%
1$
0#
0"
0!
$end
#5
0*
0)
#10
b101 /
1*
1)
#15
0*
0)
#20
b101 .
b101 /
1*
1)
#25
0*
0)
#30
b1001 /
1*
1)
b1001 +
b1001 -
#35
0*
0)
#40
0'
b1001 .
b1001 /
1*
1)
#45
0*
0)
#50
b0 /
1*
1)
b0 +
b0 -
#55
0*
0)
#60
1"
0$
b0 .
b0 /
1*
1)
#65
0*
0)
#70
b10 /
11
1*
1)
b10 +
b10 -
#75
0*
0)
#80
0"
1#
1&
b10 .
b10 /
1*
1)
#85
0*
0)
#90
b1000 /
1*
1)
b1000 +
b1000 -
#95
0*
0)
#100
0#
0&
b1000 .
b1000 /
1*
1)
#105
0*
0)
#110
b1 /
1*
1)
b1 +
b1 -
#115
0*
0)
#120
1$
1'
b1 .
b1 /
1*
1)
#125
0*
0)
#130
1"
1#
1%
0'
1(
b1110 .
1*
1)
1,
#135
0*
0)
#140
0!
b1110 /
1*
1)
#145
0*
0)
#150
b101 /
1*
1)
b101 +
b101 -
0,
#155
0*
0)
#160
0"
0#
0%
1'
0(
b101 .
b101 /
1*
1)
#165
0*
0)
#170
b1001 /
1*
1)
b1001 +
b1001 -
#175
0*
0)
#180
0'
b1001 .
b1001 /
1*
1)
#185
0*
0)
#190
1!
1*
1)
b100 +
b100 -
#195
0*
0)
#200
1"
0$
b0 .
b0 /
1*
1)
b0 +
b0 -
#205
0*
0)
#210
b1111 /
1*
1)
#215
0*
0)
#220
0"
1#
1&
b10 .
b10 /
1*
1)
b10 +
b10 -
#225
0*
0)
#230
b1111 /
1*
1)
#235
0*
0)
#240
0#
0&
b1000 .
b1000 /
1*
1)
b1000 +
b1000 -
#245
0*
0)
#250
b1111 /
1*
1)
#255
0*
0)
#260
1%
1&
b1 .
b1 /
1*
1)
b1 +
b1 -
#265
0*
0)
#270
1*
1)
