maquina.v
module maquina(
    input clk, reset, insere,
    input [4:1] numero,
    output reg LED =0,
    output reg A, B, C, D, E, F, G
);
    parameter inicial = 4'b0000;
    parameter cinco = 4'b0101;
    parameter nove = 4'b1001;
    parameter zero = 4'b0000;
    parameter nove_final = 4'b0101;
    parameter oito = 4'b1000;
    parameter um = 4'b0001;
    parameter falha = 4'b1111;

    reg controle = 1'b0;
    reg [3:0] estado;
    reg [3:0] proximo_estado;
    
    always @(posedge clk) begin
        if (reset)  estado = inicial;
        else        estado = proximo_estado;
    end

    always @(posedge clk) begin
        if (insere == 1)begin
        case (estado)
            inicial:
                if (numero == 4'b0101) proximo_estado = cinco;
                else begin
                    if (LED) proximo_estado = falha;
                    else begin
                        proximo_estado = inicial;
                        LED = 1'b1;
                    end
                end
            cinco:
                if (LED) begin
                    if (numero == 4'b1001) proximo_estado = nove;
                    else                proximo_estado = falha;
                end
                else begin
                    if (numero == 4'b1001) proximo_estado = nove;
                    else begin
                        proximo_estado = cinco;
                        LED = 1;
                    end
                end
            nove:
                if (LED) begin
                    if (numero == 4'b0000) proximo_estado = zero;
                    else                proximo_estado = falha;
                end
                else begin
                    if (numero == 4'b0000) proximo_estado = zero;
                    else begin
                        proximo_estado = nove;
                        LED = 1;
                    end
                end
            zero:
                if (LED) begin
                    if (numero == 4'b1001) proximo_estado = nove_final;
                    else                proximo_estado = falha;
                end
                else begin
                    if (numero == 4'b1001) proximo_estado = nove_final;
                    else begin
                        proximo_estado = zero;
                        LED = 1;
                    end
                end
            nove_final:
                if (LED) begin
                    if (numero == 4'b1000) proximo_estado = oito;
                    else                proximo_estado = falha;
                end
                else begin
                    if (numero == 4'b1000) proximo_estado = oito;
                    else begin
                        proximo_estado = nove_final;
                        LED = 1;
                    end
                end
            oito:
                if(LED) begin
                    if (numero == 4'b0001) proximo_estado = um;
                    else                proximo_estado = falha;
                end
                else begin
                    if (numero == 4'b0001) proximo_estado = um;
                    else begin
                        proximo_estado = oito;
                        LED = 1;
                    end
                end
            default:
                proximo_estado = inicial;
        endcase
        end
    end
    always @(estado) begin
        if (estado == um & LED == 1) begin
            A <= 1'b0;
            B <= 1'b0;
            C <= 1'b1;
            D <= 1'b1;
            E <= 1'b0;
            F <= 1'b0;
            G <= 1'b0;
        end
        else if (estado == um & LED == 0) begin
            A <= 1'b0;
            B <= 1'b1;
            C <= 1'b0;
            D <= 1'b0;
            E <= 1'b1;
            F <= 1'b0;
            G <= 1'b0;
        end
        else if (estado == falha) begin
            A <= 1'b0;
            B <= 1'b1;
            C <= 1'b1;
            D <= 1'b1;
            E <= 1'b0;
            F <= 1'b0;
            G <= 1'b0;
        end
        else begin
            A <= ((~numero[4])&numero[2])|((~numero[4])&(~numero[3])&(~numero[1]))|((~numero[4])&numero[3]&numero[1])|(numero[4]&(~numero[3])&(~numero[2]));
            B <= ((~numero[4])&(~numero[3]))|((~numero[3]&(~numero[2])))|((~numero[4])&(~numero[2])&(~numero[1]))|((~numero[4])&numero[2]&numero[1]);
            C <= ((~numero[3])&(~numero[2]))|((~numero[4])&numero[1])|((~numero[4])&numero[3]);
            D <= ((~numero[4])&(~numero[3])&(~numero[1]))|((~numero[4])&(~numero[3])&numero[2])|((~numero[4])&numero[2]&(~numero[1]))|(numero[4]&(~numero[3])&(~numero[2]))|((~numero[4])&(numero[3])&(~numero[2])&numero[1]);
            E <= ((~numero[3])&(~numero[2])&(~numero[1]))|((~numero[4])&numero[2]&(~numero[1]));
            F <= ((~numero[4])&(~numero[2])&(~numero[1]))|((~numero[4])&numero[3]&(~numero[2]))|((~numero[4])&numero[3]&(~numero[1]))|(numero[4]&(~numero[3])&(~numero[2]));
            G <= (numero[4]|((~numero[3])&numero[2])|(numero[2]&(~numero[1]))|(numero[3]&(~numero[2])));
        end
    end
        // case(numero)
        // inicial: begin
        //     if(numero == 4'b0000)
        // end
endmodule

maquina_tb.v
`include "./maquina.v"
module maquina_tb ();
    reg clk, reset, insere;
    reg [4:1] numero;
    wire LED, A, B, C, D, E, F, G;


    maquina tb_maquina(.clk(clk), .reset(reset), .insere(insere), .numero(numero), .LED(LED), .A(A), .B(B), .C(C), .D(D), .E(E), .F(F), .G(G));

    always begin
        #5
        clk = ~clk;
    end
    initial begin
        $dumpfile("maquina.vcd");
        $dumpvars;
        $display("numero A B C D E F G LED");
        $monitor("%b%b%b%b   %b %b %b %b %b %b %b %b",numero[4],numero[3], numero[2], numero[1], A,B,C,D,E,F,G,LED);

        reset = 0; insere = 0; clk = 0;
        #5
        reset = 1'b1;
        #5
        reset = 1'b0;
        #5
        numero = 4'b0101;
        #5
        insere = 1'b1;
        #5
        insere = 1'b0;

        #5
        numero = 4'b1001;;
        #5
        insere = 1'b1;
        #5
        insere = 1'b0;

        #5
        numero = 4'b0000;;
        #5
        insere = 1'b1;
        #5
        insere = 1'b0;

        #5
        numero = 4'b1001;;
        #5
        insere = 1'b1;
        #5
        insere = 1'b0;

        #5
        numero = 4'b1000;
        #5
        insere = 1'b1;
        #5
        insere = 1'b0;

        #5
        numero = 4'b0001;
        #5
        insere = 1'b1;
        #5
        insere = 1'b0;

//-------------------------------------------------------------------------------------
        #5
        reset = 1'b1;
        #5
        reset = 1'b0;
        #5
        numero[4] = 1'b0; numero[3] = 1'b0; numero[2] = 1'b0; numero[1] = 1'b1;
        #5
        insere = 1'b1;
        #5
        insere = 1'b0;

        #5
        numero[4] = 1'b1; numero[3] = 1'b0; numero[2] = 1'b0; numero[1] = 1'b1;
        #5
        insere = 1'b1;
        #5
        insere = 1'b0;

        #5
        numero[4] = 1'b0; numero[3] = 1'b0; numero[2] = 1'b0; numero[1] = 1'b0;
        #5
        insere = 1'b1;
        #5
        insere = 1'b0;

        #5
        numero[4] = 1'b1; numero[3] = 1'b0; numero[2] = 1'b0; numero[1] = 1'b1;
        #5
        insere = 1'b1;
        #5
        insere = 1'b0;

        #5
        numero[4] = 1'b1; numero[3] = 1'b0; numero[2] = 1'b0; numero[1] = 1'b0;
        #5
        insere = 1'b1;
        #5
        insere = 1'b0;

        numero[4] = 1'b0; numero[3] = 1'b0; numero[2] = 1'b0; numero[1] = 1'b1;
        #5
        insere = 1'b1;
        #5
        insere = 1'b0;

        #10 $finish;
    end
endmodule

maquina.vcd
$date
	Tue Jan 14 11:41:40 2025
$end
$version
	Icarus Verilog
$end
$timescale
	1s
$end
$scope module maquina_tb $end
$var wire 1 ! LED $end
$var wire 1 " G $end
$var wire 1 # F $end
$var wire 1 $ E $end
$var wire 1 % D $end
$var wire 1 & C $end
$var wire 1 ' B $end
$var wire 1 ( A $end
$var reg 1 ) clk $end
$var reg 1 * insere $end
$var reg 4 + numero [4:1] $end
$var reg 1 , reset $end
$scope module tb_maquina $end
$var wire 1 ) clk $end
$var wire 1 * insere $end
$var wire 4 - numero [4:1] $end
$var wire 1 , reset $end
$var reg 1 ( A $end
$var reg 1 ' B $end
$var reg 1 & C $end
$var reg 1 % D $end
$var reg 1 $ E $end
$var reg 1 # F $end
$var reg 1 " G $end
$var reg 1 ! LED $end
$var reg 1 . controle $end
$var reg 4 / estado [3:0] $end
$var reg 4 0 proximo_estado [3:0] $end
$upscope $end
$upscope $end
$enddefinitions $end
#0
$dumpvars
bx 0
bx /
0.
bx -
0,
bx +
0*
0)
x(
x'
x&
x%
x$
x#
x"
0!
$end
#5
b0 /
1,
1)
#10
0,
0)
#15
1"
1#
0$
1%
1&
0'
1(
bx /
b101 +
b101 -
1)
#20
1*
0)
#25
0*
1)
#30
b1001 +
b1001 -
0)
#35
b0 0
1*
1)
#40
0*
0)
#45
0"
1$
1'
b0 /
b0 +
b0 -
1)
#50
1*
0)
#55
0*
1)
#60
b1001 +
b1001 -
0)
#65
1!
1*
1)
#70
0*
0)
#75
b1000 +
b1000 -
1)
#80
1*
0)
#85
0*
1)
#90
b1 +
b1 -
0)
#95
b1111 0
1*
1)
#100
0*
0)
#105
1,
1)
#110
0,
0)
#115
0#
0$
0(
b1111 /
1)
#120
1*
0)
#125
0*
1)
#130
b1001 +
b1001 -
0)
#135
b0 0
1*
1)
#140
0*
0)
#145
1#
1$
1(
b0 /
b0 +
b0 -
1)
#150
1*
0)
#155
0*
1)
#160
b1001 +
b1001 -
0)
#165
0#
0$
0(
b1111 /
b1111 0
1*
1)
#170
0*
0)
#175
b1000 +
b1000 -
1)
#180
1*
0)
#185
b1 +
b1 -
0*
1)
#190
1*
0)
#195
0*
1)
