modulo_maquina_simulacao/maquina.v
module maquina(
    //declaração das entradas e saídas
    input clk, reset, insere,
    input [4:1] numero,
    output reg LED =0,
    output reg A, B, C, D, E, F, G
);
//assinalamento de estados
    parameter inicial = 4'b0000;
    parameter cinco = 4'b0001;
    parameter nove = 4'b0010;
    parameter zero = 4'b0011;
    parameter nove_final= 4'b0100;
    parameter oito = 4'b0101;
    parameter um = 4'b1100;
    parameter falha = 4'b1111;

//variáveis de estado
    reg [3:0] estado;
    reg [3:0] proximo_estado;
    
//transição entre estados
    always @(posedge clk) begin
        if (reset == 1'b1)  begin
            estado <= inicial;
        end
        else begin 
            estado <= proximo_estado;
        end
    end

    always @(posedge clk) begin
		if (insere == 1'b1) begin
        //assinala o próximo_estadon para a transição de acordo com o estado atual, o numero inserido e o LED
        case (estado)
            um:
                proximo_estado = um;
            falha:
                proximo_estado = falha;
            inicial:
                if (numero == 4'b0101) proximo_estado = cinco;
                else begin
                    if (LED) proximo_estado = falha;
                    else begin
                        proximo_estado = inicial;
                        LED = 1'b1;
                    end
                end
            cinco:
                if (LED) begin
                    if (numero == 4'b1001) proximo_estado = nove;
                    else                proximo_estado = falha;
                end
                else begin
                    if (numero == 4'b1001) proximo_estado = nove;
                    else begin
                        proximo_estado = cinco;
                        LED = 1;
                    end
                end
            nove:
                if (LED) begin
                    if (numero == 4'b0000) proximo_estado =zero;
                    else                proximo_estado = falha;
                end
                else begin
                    if (numero == 4'b0000) proximo_estado =zero;
                    else begin
                        proximo_estado = nove;
                        LED = 1;
                    end
                end
            zero: begin
                if (LED) begin
                    if (numero == 4'b1001) proximo_estado = nove_final;
                    else                proximo_estado = falha;
                end
                else begin
                    if (numero == 4'b1001) proximo_estado = nove_final;
                    else begin
                        proximo_estado = zero;
                        LED = 1;
                    end
                end
            end
            nove_final:
                if (LED) begin
                    if (numero == 4'b1000) proximo_estado = oito;
                    else                proximo_estado = falha;
                end
                else begin
                    if (numero == 4'b1000) proximo_estado = oito;
                    else begin
                        proximo_estado = nove_final;
                        LED = 1;
                    end
                end
            oito:
                if(LED) begin
                    if (numero == 4'b0001) proximo_estado = um;
                    else                proximo_estado = falha;
                end
                else begin
                    if (numero == 4'b0001) proximo_estado = um;
                    else begin
                        proximo_estado = oito;
                        LED = 1;
                    end
                end
            default:
                proximo_estado = inicial;
        endcase
		  end

		  else begin
        //reseta o LED quando a máquina reseta
		  if (reset == 1'b1) begin
					proximo_estado = inicial;
					LED = 0;
			end
		  end
    end

//bloco responsável por configurar os segmentos do display de acordo com: 
//o reset, o insere, o estado atual, o LED e a entrada numero
    always @(clk) begin
		  if (reset == 1'b1) begin
			A <= 1'b1;
            B <= 1'b1;
            C <= 1'b1;
            D <= 1'b1;
            E <= 1'b1;
            F <= 1'b1;
            G <= 1'b0;
		  
		  end
        else if (estado == um & LED == 1) begin
            A <= 1'b1;
            B <= 1'b1;
            C <= 1'b0;
            D <= 1'b0;
            E <= 1'b1;
            F <= 1'b1;
            G <= 1'b1;
        end

        else if (estado == um & LED == 0) begin
            A <= 1'b1;
            B <= 1'b0;
            C <= 1'b1;
            D <= 1'b1;
            E <= 1'b0;
            F <= 1'b1;
            G <= 1'b1;
        end
        else if (estado == falha) begin
            A <= 1'b1;
            B <= 1'b0;
            C <= 1'b0;
            D <= 1'b0;
            E <= 1'b1;
            F <= 1'b1;
            G <= 1'b1;
        end
        else if (insere == 1'b1) begin
            A <= (((~numero[4])&numero[2])|((~numero[4])&(~numero[3])&(~numero[1]))|((~numero[4])&numero[3]&numero[1])|(numero[4]&(~numero[3])&(~numero[2])));
            B <= (((~numero[4])&(~numero[3]))|((~numero[3]&(~numero[2])))|((~numero[4])&(~numero[2])&(~numero[1]))|((~numero[4])&numero[2]&numero[1]));
            C <= (((~numero[3])&(~numero[2]))|((~numero[4])&numero[1])|((~numero[4])&numero[3]));
            D <= (((~numero[4])&(~numero[3])&(~numero[1]))|((~numero[4])&(~numero[3])&numero[2])|((~numero[4])&numero[2]&(~numero[1]))|(numero[4]&(~numero[3])&(~numero[2]))|((~numero[4])&(numero[3])&(~numero[2])&numero[1]));
            E <= (((~numero[3])&(~numero[2])&(~numero[1]))|((~numero[4])&numero[2]&(~numero[1])));
            F <= (((~numero[4])&(~numero[2])&(~numero[1]))|((~numero[4])&numero[3]&(~numero[2]))|((~numero[4])&numero[3]&(~numero[1]))|(numero[4]&(~numero[3])&(~numero[2])));
            G <= ((numero[4]|((~numero[3])&numero[2])|(numero[2]&(~numero[1]))|(numero[3]&(~numero[2]))));
        end
    end
endmodule

modulo_maquina_simulacao/maquina_tb.v
`include "./maquina.v"
module maquina_tb ();
    reg clk, reset, insere;
    reg [4:1] numero;
    wire LED, A, B, C, D, E, F, G;


    maquina tb_maquina(.clk(clk), .reset(reset), .insere(insere), .numero(numero), .LED(LED), .A(A), .B(B), .C(C), .D(D), .E(E), .F(F), .G(G));

    always begin
        #5
        clk = ~clk;
    end
    initial begin
        $dumpfile("maquina.vcd");
        $dumpvars;
        $display("numero A B C D E F G LED");
        $monitor("%b%b%b%b   %b %b %b %b %b %b %b %b %b",numero[4],numero[3], numero[2], numero[1], A,B,C,D,E,F,G,LED,reset);

        reset = 1'b1;
        clk = 1; insere =1;
        numero = 4'b0101;
        reset = 0;

        #15
        insere =0;
        #10
        insere =1;
        numero = 4'b1001;


        #10
        insere =0;

        #10
        numero = 4'b0000;
        insere =1;

        #10
        insere =0;

        #10
        numero = 4'b1001;
        insere =1;

        #10
        insere =0;

        #10
        numero = 4'b1000;
        insere =1;

        #10
        insere =0;
        #10
        numero = 4'b0001;
        insere =1;

        #10
        insere =0;
        #15
        reset= 1;
        #15
//-------------------------------------------------------------------------------------
        reset = 1'b0;
        clk = 1; insere =1;
        numero = 4'b0101;

        #15
        insere =0;
        #10
        insere =1;
        numero = 4'b1001;

        #10
        insere =0;

        #10
        numero = 4'b0000;
        insere =1;

        #10
        insere =0;

        #10
        numero = 4'b0001;
        insere =1;

        #10
        insere =0;

        #10
        numero = 4'b1001;
        insere =1;

        #10
        insere =0;

        #10
        numero = 4'b1000;
        insere =1;

        #10
        insere =0;
        #10
        numero = 4'b0001;
        insere =1;
        #10
        insere =0;
        #15
        reset= 1;
        #15
//-------------------------------------------------------------------------------------

        reset = 1'b0;
        clk = 1; insere = 1;
        numero = 4'b0101;

        #15
        insere =0;
        #10
        insere =1;
        numero = 4'b1001;

        #10
        insere =0;

        #10
        numero = 4'b0000;
        insere =1;

        #10
        insere =0;

        #10
        numero = 4'b0001;
        insere =1;

        #10
        insere =0;

        #10
        numero = 4'b0010;
        insere =1;

        #10
        insere =0;

        #10
        numero = 4'b1000;
        insere =1;

        #10
        insere =0;
        #10
        numero = 4'b0001;
        insere =1;
        #10
        insere =0;
        #15
        #40 $finish;
    end
endmodule

modulo_maquina_simulacao/codigo/maquina.vcd
$date
	Mon Jan 20 22:48:47 2025
$end
$version
	Icarus Verilog
$end
$timescale
	1s
$end
$scope module maquina_tb $end
$var wire 1 ! LED $end
$var wire 1 " G $end
$var wire 1 # F $end
$var wire 1 $ E $end
$var wire 1 % D $end
$var wire 1 & C $end
$var wire 1 ' B $end
$var wire 1 ( A $end
$var reg 1 ) clk $end
$var reg 1 * insere $end
$var reg 4 + numero [4:1] $end
$var reg 1 , reset $end
$scope module tb_maquina $end
$var wire 1 ) clk $end
$var wire 1 * insere $end
$var wire 4 - numero [4:1] $end
$var wire 1 , reset $end
$var reg 1 ( A $end
$var reg 1 ' B $end
$var reg 1 & C $end
$var reg 1 % D $end
$var reg 1 $ E $end
$var reg 1 # F $end
$var reg 1 " G $end
$var reg 1 ! LED $end
$var reg 4 . estado [3:0] $end
$var reg 4 / proximo_estado [3:0] $end
$upscope $end
$upscope $end
$enddefinitions $end
#0
$dumpvars
b0 /
b0 .
b101 -
0,
b101 +
1*
1)
1(
0'
1&
1%
0$
1#
1"
0!
$end
#5
0)
#10
b1 /
1)
#15
0)
0*
#20
b1 .
1)
#25
1'
0)
b1001 +
b1001 -
1*
#30
b10 /
1)
#35
0)
0*
#40
b10 .
1)
#45
0"
1$
0)
1*
b0 +
b0 -
#50
b11 /
1)
#55
0)
0*
#60
b11 .
1)
#65
1"
0$
0)
1*
b1001 +
b1001 -
#70
b100 /
1)
#75
0)
0*
#80
b100 .
1)
#85
1$
0)
1*
b1000 +
b1000 -
#90
b101 /
1)
#95
0)
0*
#100
b101 .
1)
#105
0"
0#
0$
0%
0(
0)
1*
b1 +
b1 -
#110
b1100 /
1)
#115
0)
0*
#120
b1100 .
1)
#125
1"
1#
1%
0'
1(
0)
#130
0"
1$
1'
b0 .
b0 /
1)
1,
#135
0)
#140
1)
#145
1"
0$
0'
0)
b101 +
b101 -
1*
0,
#150
b1 /
1)
#155
0)
#160
b1 .
1)
0*
#165
0)
#170
1'
b10 /
1)
b1001 +
b1001 -
1*
#175
0)
#180
b10 .
1)
0*
#185
0)
#190
0"
1$
b11 /
1)
1*
b0 +
b0 -
#195
0)
#200
b11 .
1)
0*
#205
0)
#210
0#
0$
0%
0(
1!
1)
1*
b1 +
b1 -
#215
0)
#220
1)
0*
#225
0)
#230
1"
1#
1%
1(
b100 /
1)
1*
b1001 +
b1001 -
#235
0)
#240
b100 .
1)
0*
#245
0)
#250
1$
b101 /
1)
1*
b1000 +
b1000 -
#255
0)
#260
b101 .
1)
0*
#265
0)
#270
0"
0#
0$
0%
0(
b1100 /
1)
1*
b1 +
b1 -
#275
0)
#280
b1100 .
1)
0*
#285
1"
1#
1$
0&
1(
0)
#290
1)
#295
0"
1%
1&
0)
1,
#300
b0 .
0!
b0 /
1)
#305
0)
#310
1"
0$
0'
b1 /
b101 +
b101 -
1*
0)
0,
#315
b1 .
1)
#320
0)
#325
1)
0*
#330
0)
#335
1'
b10 .
b10 /
1)
b1001 +
b1001 -
1*
#340
0)
#345
1)
0*
#350
0)
#355
0"
1$
b11 .
b11 /
1)
1*
b0 +
b0 -
#360
0)
#365
1)
0*
#370
0)
#375
0#
0$
0%
0(
1!
1)
1*
b1 +
b1 -
#380
0)
#385
1)
0*
#390
0)
#395
1"
1$
1%
0&
1(
b1111 .
b1111 /
1)
1*
b10 +
b10 -
#400
1#
0%
0'
0)
#405
1)
0*
#410
0)
#415
1)
1*
b1000 +
b1000 -
#420
0)
#425
1)
0*
#430
0)
#435
1)
1*
b1 +
b1 -
#440
0)
#445
1)
0*
